cryptoagents_a2a_devkit/__init__.py
cryptoagents_a2a_devkit/handlers.py
cryptoagents_a2a_devkit-1.0.4.dist-info/METADATA
cryptoagents_a2a_devkit-1.0.4.dist-info/WHEEL
cryptoagents_a2a_devkit-1.0.4.dist-info/licenses/LICENSE
cryptoagents_a2a_devkit-1.0.4.dist-info/RECORD
